honeybee_3dm/__init__.py
honeybee_3dm/cli.py
honeybee_3dm/config.py
honeybee_3dm/face.py
honeybee_3dm/grid.py
honeybee_3dm/helper.py
honeybee_3dm/layer.py
honeybee_3dm/material.py
honeybee_3dm/model.py
honeybee_3dm/togeometry.py
honeybee_3dm-0.4.69.dist-info/LICENSE
honeybee_3dm-0.4.69.dist-info/METADATA
honeybee_3dm-0.4.69.dist-info/WHEEL
honeybee_3dm-0.4.69.dist-info/entry_points.txt
honeybee_3dm-0.4.69.dist-info/top_level.txt
honeybee_3dm-0.4.69.dist-info/RECORD
