Metadata-Version: 2.1
Name: honeybee-3dm
Version: 0.4.69
Summary: Honeybee extension for translating to and from Rhino 3dm.
Home-page: https://github.com/ladybug-tools/honeybee-3dm
Author: Ladybug Tools
Author-email: info@ladybug.tools
License: AGPL-3.0
Platform: UNKNOWN
Classifier: Programming Language :: Python :: 3.7
Classifier: Programming Language :: Python :: Implementation :: CPython
Classifier: License :: OSI Approved :: GNU Affero General Public License v3
Classifier: Operating System :: OS Independent
License-File: LICENSE
Requires-Dist: lbt-honeybee (>=0.6.115)
Requires-Dist: rhino3dm (>=7.7.0)
